{
  "students": [
    {
      "id": "STU-001",
      "name": "DEMO Student A",
      "major": "Computer Science (BS)",
      "minor": "Data Science",
      "campus": "Tempe",
      "year": "Junior",
      "gpa": 3.42,
      "credits_completed": 78,
      "credits_required": 120,
      "enrollment_status": "Full-time",
      "residency": "In-state",
      "gen_studies_remaining": ["GSC", "HU"],
      "current_courses": ["CSE 340", "CSE 355", "MAT 343", "ENG 302"],
      "engagement_score": 0.88,
      "attendance_rate": 0.94,
      "advisor_notes": "Strong performer. Interested in AI/ML research. Considering MS program.",
      "risk_level": "low",
      "financial_aid": {"pell_grant": 0, "merit_scholarship": 8000, "loans": 12000, "work_study": true}
    },
    {
      "id": "STU-002",
      "name": "DEMO Student B",
      "major": "Biological Sciences (BS)",
      "minor": null,
      "campus": "Tempe",
      "year": "Sophomore",
      "gpa": 2.31,
      "credits_completed": 34,
      "credits_required": 120,
      "enrollment_status": "Full-time",
      "residency": "Out-of-state",
      "gen_studies_remaining": ["GSB", "GSC", "GSD", "SQ", "L"],
      "current_courses": ["BIO 281", "CHM 233", "PHY 121", "ASU 150"],
      "engagement_score": 0.52,
      "attendance_rate": 0.71,
      "advisor_notes": "GPA declining from 2.8 freshman year. Missing office hours. May need tutoring referral.",
      "risk_level": "high",
      "financial_aid": {"pell_grant": 6895, "merit_scholarship": 2000, "loans": 28000, "work_study": false}
    },
    {
      "id": "STU-003",
      "name": "DEMO Student C",
      "major": "Nursing (BSN)",
      "minor": null,
      "campus": "Downtown Phoenix",
      "year": "Senior",
      "gpa": 3.87,
      "credits_completed": 102,
      "credits_required": 120,
      "enrollment_status": "Full-time",
      "residency": "In-state",
      "gen_studies_remaining": [],
      "current_courses": ["NUR 442", "NUR 451", "NUR 460", "NUR 472"],
      "engagement_score": 0.96,
      "attendance_rate": 0.99,
      "advisor_notes": "Top of cohort. Clinical rotations at Banner Health excellent. Grad school candidate.",
      "risk_level": "low",
      "financial_aid": {"pell_grant": 0, "merit_scholarship": 14000, "loans": 8000, "work_study": false}
    },
    {
      "id": "STU-004",
      "name": "DEMO Student D",
      "major": "Mechanical Engineering (BSE)",
      "minor": "Sustainability",
      "campus": "Polytechnic",
      "year": "Freshman",
      "gpa": 3.15,
      "credits_completed": 16,
      "credits_required": 128,
      "enrollment_status": "Full-time",
      "residency": "In-state",
      "gen_studies_remaining": ["GSA", "GSB", "GSC", "GSD", "HU", "SB", "L", "MA", "CS"],
      "current_courses": ["MAT 265", "PHY 121", "FSE 100", "ENG 101"],
      "engagement_score": 0.75,
      "attendance_rate": 0.88,
      "advisor_notes": "Adjusting to college life. Joined EPICS design team. Calculus is a concern.",
      "risk_level": "moderate",
      "financial_aid": {"pell_grant": 3000, "merit_scholarship": 6000, "loans": 5500, "work_study": true}
    },
    {
      "id": "STU-005",
      "name": "DEMO Student E",
      "major": "Business Data Analytics (BS)",
      "minor": "Information Technology",
      "campus": "West",
      "year": "Junior",
      "gpa": 3.68,
      "credits_completed": 72,
      "credits_required": 120,
      "enrollment_status": "Full-time",
      "residency": "Out-of-state",
      "gen_studies_remaining": ["HU"],
      "current_courses": ["CIS 365", "CIS 340", "WPC 348", "MKT 302"],
      "engagement_score": 0.91,
      "attendance_rate": 0.95,
      "advisor_notes": "Dean's List. Active in Business Analytics Club. Internship at local fintech firm.",
      "risk_level": "low",
      "financial_aid": {"pell_grant": 0, "merit_scholarship": 10000, "loans": 18000, "work_study": false}
    },
    {
      "id": "STU-006",
      "name": "DEMO Student F",
      "major": "Psychology (BA)",
      "minor": null,
      "campus": "Tempe",
      "year": "Senior",
      "gpa": 2.05,
      "credits_completed": 98,
      "credits_required": 120,
      "enrollment_status": "Part-time",
      "residency": "In-state",
      "gen_studies_remaining": ["MA"],
      "current_courses": ["PSY 410", "PSY 394"],
      "engagement_score": 0.38,
      "attendance_rate": 0.62,
      "advisor_notes": "Working 30+ hrs/week off-campus. Financial stress. Considering stopping out. Needs immediate intervention.",
      "risk_level": "critical",
      "financial_aid": {"pell_grant": 6895, "merit_scholarship": 0, "loans": 32000, "work_study": false}
    }
  ]
}
